rpi_shtx_influx/__init__.py
rpi_shtx_influx/temperature.py
rpi_shtx_influx/tool.py
rpi_shtx_influx-1.7.dist-info/entry_points.txt
rpi_shtx_influx-1.7.dist-info/LICENSE.md
rpi_shtx_influx-1.7.dist-info/WHEEL
rpi_shtx_influx-1.7.dist-info/METADATA
rpi_shtx_influx-1.7.dist-info/RECORD
